aoikwinwhich/aoikww.py
aoikwinwhich/__init__.py
aoikwinwhich/__main__.py
AoikWinWhich-0.1.0.dist-info/DESCRIPTION.rst
AoikWinWhich-0.1.0.dist-info/entry_points.txt
AoikWinWhich-0.1.0.dist-info/METADATA
AoikWinWhich-0.1.0.dist-info/metadata.json
AoikWinWhich-0.1.0.dist-info/RECORD
AoikWinWhich-0.1.0.dist-info/top_level.txt
AoikWinWhich-0.1.0.dist-info/WHEEL
